chaos_tickets/__init__.py
chaos_tickets/apps.py
chaos_tickets/models.py
chaos_tickets/urls.py
chaos_tickets/views.py
chaos_tickets/static/css/chaos_tickets.css
chaos_tickets/static/js/chaos_tickets.js
chaos_tickets/templates/chaos_tickets/base.html
django_chaos_tickets-0.1.0.dist-info/DESCRIPTION.rst
django_chaos_tickets-0.1.0.dist-info/METADATA
django_chaos_tickets-0.1.0.dist-info/RECORD
django_chaos_tickets-0.1.0.dist-info/WHEEL
django_chaos_tickets-0.1.0.dist-info/metadata.json
django_chaos_tickets-0.1.0.dist-info/top_level.txt
