Metadata-Version: 2.0
Name: django-chaos-tickets
Version: 0.1.0
Summary: Ticketing system from Django and Django Chaos
Home-page: https://github.com/george-silva/django-chaos-tickets
Author: George Silva
Author-email: george@sigmageosistemas.com.br
License: MIT
Keywords: django-chaos-tickets
Platform: UNKNOWN
Classifier: Development Status :: 3 - Alpha
Classifier: Framework :: Django
Classifier: Framework :: Django :: 1.8
Classifier: Framework :: Django :: 1.9
Classifier: Framework :: Django :: 1.10
Classifier: Framework :: Django :: 1.11
Classifier: Intended Audience :: Developers
Classifier: License :: OSI Approved :: BSD License
Classifier: Natural Language :: English
Classifier: Programming Language :: Python :: 2
Classifier: Programming Language :: Python :: 2.7
Classifier: Programming Language :: Python :: 3
Classifier: Programming Language :: Python :: 3.3
Classifier: Programming Language :: Python :: 3.4
Classifier: Programming Language :: Python :: 3.5
Classifier: Programming Language :: Python :: 3.6
